{"name":"Zatherz","tagline":"Site for me and my projects","body":"### Howdy!\r\nYou've reached the website for Zatherz, the home of his projects.\r\n\r\n### Who are you?\r\nI'm an aspiring programmer. I program mostly in C and occasionally in C++ and Qt. I'm a developer for the future [Orbos](http://orbos.github.io/) Linux distro.\r\n\r\n### Where all all the projects you're talking about?\r\nLook at the sidebar on the left.","google":"","note":"Don't delete this file! It's used internally to help with page regeneration."}